dnsctl/__init__.py
dnsctl/__main__.py
dnsctl/cli.py
dnsctl/config.py
dnsctl/core.py
dnsctl/logger.py
dnsctl/templates/base.j2
dnsctl/templates/records.j2
dnsctl-0.1.1.dist-info/entry_points.txt
dnsctl-0.1.1.dist-info/LICENSE
dnsctl-0.1.1.dist-info/WHEEL
dnsctl-0.1.1.dist-info/METADATA
dnsctl-0.1.1.dist-info/RECORD
