Metadata-Version: 2.1
Name: dnsctl
Version: 0.1.1
Summary: 
Home-page: https://github.com/ollemg/dnsctl
Author: Gabriel
Author-email: gabrielmello808@gmail.com
Requires-Python: >=3.10,<4.0
Classifier: Programming Language :: Python :: 3
Classifier: Programming Language :: Python :: 3.10
Requires-Dist: Jinja2 (>=3.1.2,<4.0.0)
Requires-Dist: click (>=8.1.3,<9.0.0)
Requires-Dist: dynaconf (>=3.1.11,<4.0.0)
Requires-Dist: loguru (>=0.6.0,<0.7.0)
Requires-Dist: pathlib2 (>=2.3.7,<3.0.0)
Requires-Dist: rich-click (>=1.4,<2.0)
Project-URL: Repository, https://github.com/ollemg/dnsctl
